[{"id":"1869","Size":"205\/55R16 ","idTire":"55","options_field":"1","tireWidth":"205","tireRatio":"55","rimSize":"16"}, {"id":"1854","Size":"235\/75R15","idTire":"321","options_field":"1","tireWidth":"235","tireRatio":"75","rimSize":"15"}, {"id":"1704","Size":"215\/65R16","idTire":"6","options_field":"1","tireWidth":"215","tireRatio":"65","rimSize":"16"}, {"id":"1703","Size":"205\/65R16","idTire":"6","options_field":"1","tireWidth":"205","tireRatio":"65","rimSize":"16"}, {"id":"1702","Size":"215\/65R15","idTire":"6","options_field":"1","tireWidth":"215","tireRatio":"65","rimSize":"15"}, {"id":"1701","Size":"205\/65R15","idTire":"6","options_field":"1","tireWidth":"205","tireRatio":"65","rimSize":"15"}, {"id":"1700","Size":"195\/65R15","idTire":"6","options_field":"1","tireWidth":"195","tireRatio":"65","rimSize":"15"}, {"id":"1699","Size":"185\/65R15","idTire":"6","options_field":"1","tireWidth":"185","tireRatio":"65","rimSize":"15"}, {"id":"1698","Size":"195\/65R14","idTire":"6","options_field":"1","tireWidth":"195","tireRatio":"65","rimSize":"14"}, {"id":"1697","Size":"185\/65R14","idTire":"6","options_field":"1","tireWidth":"185","tireRatio":"65","rimSize":"14"}, {"id":"1696","Size":"175\/65R14","idTire":"6","options_field":"1","tireWidth":"175","tireRatio":"65","rimSize":"14"}, {"id":"1695","Size":"235\/60R17","idTire":"6","options_field":"1","tireWidth":"235","tireRatio":"60","rimSize":"17"}, {"id":"1694","Size":"225\/60R17","idTire":"6","options_field":"1","tireWidth":"225","tireRatio":"60","rimSize":"17"}, {"id":"1693","Size":"215\/60R17","idTire":"6","options_field":"1","tireWidth":"215","tireRatio":"60","rimSize":"17"}, {"id":"1692","Size":"235\/60R16","idTire":"6","options_field":"1","tireWidth":"235","tireRatio":"60","rimSize":"16"}, {"id":"1691","Size":"225\/60R16","idTire":"6","options_field":"1","tireWidth":"225","tireRatio":"60","rimSize":"16"}, {"id":"1690","Size":"215\/60R16","idTire":"6","options_field":"1","tireWidth":"215","tireRatio":"60","rimSize":"16"}, {"id":"1689","Size":"205\/60R16","idTire":"6","options_field":"1","tireWidth":"205","tireRatio":"60","rimSize":"16"}, {"id":"1688","Size":"225\/60R15","idTire":"6","options_field":"1","tireWidth":"225","tireRatio":"60","rimSize":"15"}, {"id":"1687","Size":"215\/60R15","idTire":"6","options_field":"1","tireWidth":"215","tireRatio":"60","rimSize":"15"}, {"id":"1686","Size":"205\/60R15","idTire":"6","options_field":"1","tireWidth":"205","tireRatio":"60","rimSize":"15"}, {"id":"1685","Size":"195\/60R15","idTire":"6","options_field":"1","tireWidth":"195","tireRatio":"60","rimSize":"15"}, {"id":"1684","Size":"185\/60R15","idTire":"6","options_field":"1","tireWidth":"185","tireRatio":"60","rimSize":"15"}, {"id":"1683","Size":"215\/60R14","idTire":"6","options_field":"1","tireWidth":"215","tireRatio":"60","rimSize":"14"}, {"id":"1682","Size":"205\/60R14","idTire":"6","options_field":"1","tireWidth":"205","tireRatio":"60","rimSize":"14"}, {"id":"1681","Size":"195\/60R14","idTire":"6","options_field":"1","tireWidth":"195","tireRatio":"60","rimSize":"14"}, {"id":"1680","Size":"185\/60R14","idTire":"6","options_field":"1","tireWidth":"185","tireRatio":"60","rimSize":"14"}, {"id":"1679","Size":"185\/60R13","idTire":"6","options_field":"1","tireWidth":"185","tireRatio":"60","rimSize":"13"}, {"id":"1678","Size":"235\/55R17","idTire":"6","options_field":"1","tireWidth":"235","tireRatio":"55","rimSize":"17"}, {"id":"1677","Size":"225\/55R17","idTire":"6","options_field":"1","tireWidth":"225","tireRatio":"55","rimSize":"17"}, {"id":"1676","Size":"215\/55R17","idTire":"6","options_field":"1","tireWidth":"215","tireRatio":"55","rimSize":"17"}, {"id":"1675","Size":"225\/55R16","idTire":"6","options_field":"1","tireWidth":"225","tireRatio":"55","rimSize":"16"}, {"id":"1674","Size":"215\/55R16","idTire":"6","options_field":"1","tireWidth":"215","tireRatio":"55","rimSize":"16"}, {"id":"1673","Size":"205\/55R16","idTire":"6","options_field":"1","tireWidth":"205","tireRatio":"55","rimSize":"16"}, {"id":"1672","Size":"225\/50R17","idTire":"6","options_field":"1","tireWidth":"225","tireRatio":"50","rimSize":"17"}, {"id":"1671","Size":"215\/50R17","idTire":"6","options_field":"1","tireWidth":"215","tireRatio":"50","rimSize":"17"}, {"id":"1670","Size":"205\/50R17","idTire":"6","options_field":"1","tireWidth":"205","tireRatio":"50","rimSize":"17"}, {"id":"1669","Size":"245\/50R16","idTire":"6","options_field":"1","tireWidth":"245","tireRatio":"50","rimSize":"16"}, {"id":"1668","Size":"225\/50R16","idTire":"6","options_field":"1","tireWidth":"225","tireRatio":"50","rimSize":"16"}, {"id":"1667","Size":"205\/50R16","idTire":"6","options_field":"1","tireWidth":"205","tireRatio":"50","rimSize":"16"}, {"id":"1666","Size":"195\/50R16","idTire":"6","options_field":"1","tireWidth":"195","tireRatio":"50","rimSize":"16"}, {"id":"1665","Size":"205\/50R15","idTire":"6","options_field":"1","tireWidth":"205","tireRatio":"50","rimSize":"15"}, {"id":"1664","Size":"195\/50R15","idTire":"6","options_field":"1","tireWidth":"195","tireRatio":"50","rimSize":"15"}, {"id":"1663","Size":"225\/70R16","idTire":"229","options_field":"1","tireWidth":"225","tireRatio":"70","rimSize":"16"}, {"id":"1662","Size":"215\/70R15","idTire":"229","options_field":"1","tireWidth":"215","tireRatio":"70","rimSize":"15"}, {"id":"1661","Size":"205\/70R15","idTire":"229","options_field":"1","tireWidth":"205","tireRatio":"70","rimSize":"15"}, {"id":"1660","Size":"195\/70R14","idTire":"229","options_field":"1","tireWidth":"195","tireRatio":"70","rimSize":"14"}, {"id":"1659","Size":"185\/70R14","idTire":"229","options_field":"1","tireWidth":"185","tireRatio":"70","rimSize":"14"}, {"id":"1658","Size":"175\/70R13","idTire":"229","options_field":"1","tireWidth":"175","tireRatio":"70","rimSize":"13"}, {"id":"1011","Size":"225\/45R18 ","idTire":"52","options_field":"1","tireWidth":"225","tireRatio":"45","rimSize":"18"}, {"id":"1010","Size":"205\/55R16 ","idTire":"52","options_field":"1","tireWidth":"205","tireRatio":"55","rimSize":"16"}, {"id":"1009","Size":"195\/65R15 ","idTire":"52","options_field":"1","tireWidth":"195","tireRatio":"65","rimSize":"15"}, {"id":"1868","Size":"205\/55R16","idTire":"55","options_field":"1","tireWidth":"205","tireRatio":"55","rimSize":"16"}, {"id":"1867","Size":"235\/45R18","idTire":"55","options_field":"1","tireWidth":"235","tireRatio":"45","rimSize":"18"}, {"id":"1866","Size":"215\/55R17","idTire":"55","options_field":"1","tireWidth":"215","tireRatio":"55","rimSize":"17"}, {"id":"1865","Size":"205\/60R16","idTire":"55","options_field":"1","tireWidth":"205","tireRatio":"60","rimSize":"16"}, {"id":"1864","Size":"205\/60R16","idTire":"55","options_field":"1","tireWidth":"205","tireRatio":"60","rimSize":"16"}, {"id":"1863","Size":"225\/40R18","idTire":"55","options_field":"1","tireWidth":"225","tireRatio":"40","rimSize":"18"}, {"id":"1623","Size":"215\/65R17","idTire":"19","options_field":"1","tireWidth":"215","tireRatio":"65","rimSize":"17"}, {"id":"1622","Size":"235\/65R16","idTire":"19","options_field":"1","tireWidth":"235","tireRatio":"65","rimSize":"16"}, {"id":"1621","Size":"225\/65R16","idTire":"19","options_field":"1","tireWidth":"225","tireRatio":"65","rimSize":"16"}, {"id":"1620","Size":"215\/65R16","idTire":"19","options_field":"1","tireWidth":"215","tireRatio":"65","rimSize":"16"}, {"id":"1619","Size":"205\/65R16","idTire":"19","options_field":"1","tireWidth":"205","tireRatio":"65","rimSize":"16"}, {"id":"1618","Size":"215\/65R15","idTire":"19","options_field":"1","tireWidth":"215","tireRatio":"65","rimSize":"15"}, {"id":"1617","Size":"205\/65R15","idTire":"19","options_field":"1","tireWidth":"205","tireRatio":"65","rimSize":"15"}, {"id":"1616","Size":"195\/65R15","idTire":"19","options_field":"1","tireWidth":"195","tireRatio":"65","rimSize":"15"}, {"id":"1615","Size":"185\/65R15","idTire":"19","options_field":"1","tireWidth":"185","tireRatio":"65","rimSize":"15"}, {"id":"1614","Size":"195\/65R14","idTire":"19","options_field":"1","tireWidth":"195","tireRatio":"65","rimSize":"14"}, {"id":"1613","Size":"185\/65R14","idTire":"19","options_field":"1","tireWidth":"185","tireRatio":"65","rimSize":"14"}, {"id":"1612","Size":"175\/65R14","idTire":"19","options_field":"1","tireWidth":"175","tireRatio":"65","rimSize":"14"}, {"id":"1611","Size":"225\/60R18","idTire":"19","options_field":"1","tireWidth":"225","tireRatio":"60","rimSize":"18"}, {"id":"1610","Size":"225\/60R17","idTire":"19","options_field":"1","tireWidth":"225","tireRatio":"60","rimSize":"17"}, {"id":"1609","Size":"215\/60R17","idTire":"19","options_field":"1","tireWidth":"215","tireRatio":"60","rimSize":"17"}, {"id":"1608","Size":"235\/60R16","idTire":"19","options_field":"1","tireWidth":"235","tireRatio":"60","rimSize":"16"}, {"id":"1607","Size":"225\/60R16","idTire":"19","options_field":"1","tireWidth":"225","tireRatio":"60","rimSize":"16"}, {"id":"1606","Size":"215\/60R16","idTire":"19","options_field":"1","tireWidth":"215","tireRatio":"60","rimSize":"16"}, {"id":"1605","Size":"205\/60R16","idTire":"19","options_field":"1","tireWidth":"205","tireRatio":"60","rimSize":"16"}, {"id":"1604","Size":"215\/60R15","idTire":"19","options_field":"1","tireWidth":"215","tireRatio":"60","rimSize":"15"}, {"id":"1603","Size":"205\/60R15","idTire":"19","options_field":"1","tireWidth":"205","tireRatio":"60","rimSize":"15"}, {"id":"1602","Size":"195\/60R15","idTire":"19","options_field":"1","tireWidth":"195","tireRatio":"60","rimSize":"15"}, {"id":"1601","Size":"185\/60R15","idTire":"19","options_field":"1","tireWidth":"185","tireRatio":"60","rimSize":"15"}, {"id":"1600","Size":"195\/60R14","idTire":"19","options_field":"1","tireWidth":"195","tireRatio":"60","rimSize":"14"}, {"id":"1599","Size":"185\/60R14","idTire":"19","options_field":"1","tireWidth":"185","tireRatio":"60","rimSize":"14"}, {"id":"1598","Size":"225\/55R18","idTire":"19","options_field":"1","tireWidth":"225","tireRatio":"55","rimSize":"18"}, {"id":"1597","Size":"215\/55R18","idTire":"19","options_field":"1","tireWidth":"215","tireRatio":"55","rimSize":"18"}, {"id":"1596","Size":"235\/55R17","idTire":"19","options_field":"1","tireWidth":"235","tireRatio":"55","rimSize":"17"}, {"id":"1595","Size":"225\/55R17","idTire":"19","options_field":"1","tireWidth":"225","tireRatio":"55","rimSize":"17"}, {"id":"1594","Size":"215\/55R17","idTire":"19","options_field":"1","tireWidth":"215","tireRatio":"55","rimSize":"17"}, {"id":"1593","Size":"225\/55R16","idTire":"19","options_field":"1","tireWidth":"225","tireRatio":"55","rimSize":"16"}, {"id":"1592","Size":"215\/55R16","idTire":"19","options_field":"1","tireWidth":"215","tireRatio":"55","rimSize":"16"}, {"id":"1591","Size":"205\/55R16","idTire":"19","options_field":"1","tireWidth":"205","tireRatio":"55","rimSize":"16"}, {"id":"1590","Size":"195\/55R16","idTire":"19","options_field":"1","tireWidth":"195","tireRatio":"55","rimSize":"16"}, {"id":"1589","Size":"195\/55R15","idTire":"19","options_field":"1","tireWidth":"195","tireRatio":"55","rimSize":"15"}, {"id":"1588","Size":"245\/50R18","idTire":"19","options_field":"1","tireWidth":"245","tireRatio":"50","rimSize":"18"}, {"id":"1587","Size":"235\/50R18","idTire":"19","options_field":"1","tireWidth":"235","tireRatio":"50","rimSize":"18"}, {"id":"1586","Size":"225\/50R18","idTire":"19","options_field":"1","tireWidth":"225","tireRatio":"50","rimSize":"18"}, {"id":"1585","Size":"235\/50R17","idTire":"19","options_field":"1","tireWidth":"235","tireRatio":"50","rimSize":"17"}, {"id":"1584","Size":"225\/50R17","idTire":"19","options_field":"1","tireWidth":"225","tireRatio":"50","rimSize":"17"}, {"id":"1583","Size":"215\/50R17","idTire":"19","options_field":"1","tireWidth":"215","tireRatio":"50","rimSize":"17"}, {"id":"1582","Size":"205\/50R17","idTire":"19","options_field":"1","tireWidth":"205","tireRatio":"50","rimSize":"17"}, {"id":"1581","Size":"225\/50R16","idTire":"19","options_field":"1","tireWidth":"225","tireRatio":"50","rimSize":"16"}, {"id":"1580","Size":"205\/50R16","idTire":"19","options_field":"1","tireWidth":"205","tireRatio":"50","rimSize":"16"}, {"id":"1579","Size":"235\/45R18","idTire":"19","options_field":"1","tireWidth":"235","tireRatio":"45","rimSize":"18"}, {"id":"1578","Size":"215\/45R18","idTire":"19","options_field":"1","tireWidth":"215","tireRatio":"45","rimSize":"18"}, {"id":"1577","Size":"255\/45R17","idTire":"19","options_field":"1","tireWidth":"255","tireRatio":"45","rimSize":"17"}, {"id":"1576","Size":"245\/45R17","idTire":"19","options_field":"1","tireWidth":"245","tireRatio":"45","rimSize":"17"}, {"id":"1575","Size":"235\/45R17","idTire":"19","options_field":"1","tireWidth":"235","tireRatio":"45","rimSize":"17"}, {"id":"1574","Size":"225\/45R17","idTire":"19","options_field":"1","tireWidth":"225","tireRatio":"45","rimSize":"17"}, {"id":"1573","Size":"215\/45R17","idTire":"19","options_field":"1","tireWidth":"215","tireRatio":"45","rimSize":"17"}, {"id":"1572","Size":"205\/45R16","idTire":"19","options_field":"1","tireWidth":"205","tireRatio":"45","rimSize":"16"}, {"id":"1571","Size":"255\/40R18","idTire":"19","options_field":"1","tireWidth":"255","tireRatio":"40","rimSize":"18"}, {"id":"1570","Size":"245\/40R18","idTire":"19","options_field":"1","tireWidth":"245","tireRatio":"40","rimSize":"18"}, {"id":"1569","Size":"235\/40R18","idTire":"19","options_field":"1","tireWidth":"235","tireRatio":"40","rimSize":"18"}, {"id":"1568","Size":"225\/40R18","idTire":"19","options_field":"1","tireWidth":"225","tireRatio":"40","rimSize":"18"}, {"id":"1567","Size":"215\/40R17","idTire":"19","options_field":"1","tireWidth":"215","tireRatio":"40","rimSize":"17"}, {"id":"1566","Size":"205\/40R17","idTire":"19","options_field":"1","tireWidth":"205","tireRatio":"40","rimSize":"17"}, {"id":"1565","Size":"215\/35R18","idTire":"19","options_field":"1","tireWidth":"215","tireRatio":"35","rimSize":"18"}, {"id":"1862","Size":"225\/45R17","idTire":"55","options_field":"1","tireWidth":"225","tireRatio":"45","rimSize":"17"}, {"id":"1861","Size":"215\/70R16","idTire":"55","options_field":"1","tireWidth":"215","tireRatio":"70","rimSize":"16"}, {"id":"1860","Size":"205\/65R16","idTire":"55","options_field":"1","tireWidth":"205","tireRatio":"65","rimSize":"16"}, {"id":"1859","Size":"225\/55R17","idTire":"55","options_field":"1","tireWidth":"225","tireRatio":"55","rimSize":"17"}, {"id":"1858","Size":"215\/55R17","idTire":"55","options_field":"1","tireWidth":"215","tireRatio":"55","rimSize":"17"}, {"id":"2137","Size":"215\/55R17","idTire":"482","options_field":"1","tireWidth":"215","tireRatio":"55","rimSize":"17"}, {"id":"2136","Size":"225\/50R17","idTire":"482","options_field":"1","tireWidth":"225","tireRatio":"50","rimSize":"17"}, {"id":"2135","Size":"215\/50R17","idTire":"482","options_field":"1","tireWidth":"215","tireRatio":"50","rimSize":"17"}, {"id":"2134","Size":"205\/50R17","idTire":"482","options_field":"1","tireWidth":"205","tireRatio":"50","rimSize":"17"}, {"id":"2133","Size":"245\/45R17","idTire":"482","options_field":"1","tireWidth":"245","tireRatio":"45","rimSize":"17"}, {"id":"2132","Size":"235\/45R17","idTire":"482","options_field":"1","tireWidth":"235","tireRatio":"45","rimSize":"17"}, {"id":"2131","Size":"225\/45R17","idTire":"482","options_field":"1","tireWidth":"225","tireRatio":"45","rimSize":"17"}, {"id":"2130","Size":"215\/45R17","idTire":"482","options_field":"1","tireWidth":"215","tireRatio":"45","rimSize":"17"}, {"id":"2129","Size":"205\/45R17","idTire":"482","options_field":"1","tireWidth":"205","tireRatio":"45","rimSize":"17"}, {"id":"2128","Size":"205\/40R17","idTire":"482","options_field":"1","tireWidth":"205","tireRatio":"40","rimSize":"17"}, {"id":"2127","Size":"225\/55R16","idTire":"482","options_field":"1","tireWidth":"225","tireRatio":"55","rimSize":"16"}, {"id":"2126","Size":"215\/55R16","idTire":"482","options_field":"1","tireWidth":"215","tireRatio":"55","rimSize":"16"}, {"id":"1447","Size":"215\/60R16","idTire":"3","options_field":"1","tireWidth":"215","tireRatio":"60","rimSize":"16"}, {"id":"1446","Size":"235\/55R17","idTire":"3","options_field":"1","tireWidth":"235","tireRatio":"55","rimSize":"17"}, {"id":"1445","Size":"225\/55R17","idTire":"3","options_field":"1","tireWidth":"225","tireRatio":"55","rimSize":"17"}, {"id":"1444","Size":"215\/55R17","idTire":"3","options_field":"1","tireWidth":"215","tireRatio":"55","rimSize":"17"}, {"id":"1443","Size":"215\/55R16","idTire":"3","options_field":"1","tireWidth":"215","tireRatio":"55","rimSize":"16"}, {"id":"1442","Size":"205\/55R16","idTire":"3","options_field":"1","tireWidth":"205","tireRatio":"55","rimSize":"16"}, {"id":"1441","Size":"245\/50R18","idTire":"3","options_field":"1","tireWidth":"245","tireRatio":"50","rimSize":"18"}, {"id":"1440","Size":"235\/50R18","idTire":"3","options_field":"1","tireWidth":"235","tireRatio":"50","rimSize":"18"}, {"id":"1439","Size":"255\/50R17","idTire":"3","options_field":"1","tireWidth":"255","tireRatio":"50","rimSize":"17"}, {"id":"1438","Size":"245\/50R17","idTire":"3","options_field":"1","tireWidth":"245","tireRatio":"50","rimSize":"17"}, {"id":"1437","Size":"225\/50R17","idTire":"3","options_field":"1","tireWidth":"225","tireRatio":"50","rimSize":"17"}, {"id":"1436","Size":"215\/50R17","idTire":"3","options_field":"1","tireWidth":"215","tireRatio":"50","rimSize":"17"}, {"id":"1435","Size":"205\/50R16","idTire":"3","options_field":"1","tireWidth":"205","tireRatio":"50","rimSize":"16"}, {"id":"1434","Size":"275\/45R19","idTire":"3","options_field":"1","tireWidth":"275","tireRatio":"45","rimSize":"19"}, {"id":"1433","Size":"245\/45R19","idTire":"3","options_field":"1","tireWidth":"245","tireRatio":"45","rimSize":"19"}, {"id":"1432","Size":"255\/45R18","idTire":"3","options_field":"1","tireWidth":"255","tireRatio":"45","rimSize":"18"}, {"id":"1431","Size":"245\/45R18","idTire":"3","options_field":"1","tireWidth":"245","tireRatio":"45","rimSize":"18"}, {"id":"1430","Size":"225\/45R18","idTire":"3","options_field":"1","tireWidth":"225","tireRatio":"45","rimSize":"18"}, {"id":"1429","Size":"245\/45R17","idTire":"3","options_field":"1","tireWidth":"245","tireRatio":"45","rimSize":"17"}, {"id":"1428","Size":"235\/45R17","idTire":"3","options_field":"1","tireWidth":"235","tireRatio":"45","rimSize":"17"}, {"id":"1427","Size":"225\/45R17","idTire":"3","options_field":"1","tireWidth":"225","tireRatio":"45","rimSize":"17"}, {"id":"1426","Size":"215\/45R17","idTire":"3","options_field":"1","tireWidth":"215","tireRatio":"45","rimSize":"17"}, {"id":"1425","Size":"205\/45R16","idTire":"3","options_field":"1","tireWidth":"205","tireRatio":"45","rimSize":"16"}, {"id":"1424","Size":"275\/40R19","idTire":"3","options_field":"1","tireWidth":"275","tireRatio":"40","rimSize":"19"}, {"id":"1423","Size":"255\/40R19","idTire":"3","options_field":"1","tireWidth":"255","tireRatio":"40","rimSize":"19"}, {"id":"1422","Size":"245\/40R19","idTire":"3","options_field":"1","tireWidth":"245","tireRatio":"40","rimSize":"19"}, {"id":"1421","Size":"245\/40R18","idTire":"3","options_field":"1","tireWidth":"245","tireRatio":"40","rimSize":"18"}, {"id":"1420","Size":"235\/40R18","idTire":"3","options_field":"1","tireWidth":"235","tireRatio":"40","rimSize":"18"}, {"id":"1419","Size":"225\/40R18","idTire":"3","options_field":"1","tireWidth":"225","tireRatio":"40","rimSize":"18"}, {"id":"1418","Size":"275\/40R17","idTire":"3","options_field":"1","tireWidth":"275","tireRatio":"40","rimSize":"17"}, {"id":"1417","Size":"255\/40R17","idTire":"3","options_field":"1","tireWidth":"255","tireRatio":"40","rimSize":"17"}, {"id":"1416","Size":"245\/40R17","idTire":"3","options_field":"1","tireWidth":"245","tireRatio":"40","rimSize":"17"}, {"id":"1415","Size":"235\/40R17","idTire":"3","options_field":"1","tireWidth":"235","tireRatio":"40","rimSize":"17"}, {"id":"1414","Size":"215\/40R17","idTire":"3","options_field":"1","tireWidth":"215","tireRatio":"40","rimSize":"17"}, {"id":"1413","Size":"205\/40R17","idTire":"3","options_field":"1","tireWidth":"205","tireRatio":"40","rimSize":"17"}, {"id":"1412","Size":"275\/35R20","idTire":"3","options_field":"1","tireWidth":"275","tireRatio":"35","rimSize":"20"}, {"id":"1411","Size":"255\/35R20","idTire":"3","options_field":"1","tireWidth":"255","tireRatio":"35","rimSize":"20"}, {"id":"1410","Size":"245\/35R20","idTire":"3","options_field":"1","tireWidth":"245","tireRatio":"35","rimSize":"20"}, {"id":"1409","Size":"225\/35R20","idTire":"3","options_field":"1","tireWidth":"225","tireRatio":"35","rimSize":"20"}, {"id":"1408","Size":"275\/35R19","idTire":"3","options_field":"1","tireWidth":"275","tireRatio":"35","rimSize":"19"}, {"id":"1407","Size":"265\/35R19","idTire":"3","options_field":"1","tireWidth":"265","tireRatio":"35","rimSize":"19"}, {"id":"1406","Size":"245\/35R19 ","idTire":"3","options_field":"1","tireWidth":"245","tireRatio":"35","rimSize":"19"}, {"id":"1405","Size":"235\/35R19 ","idTire":"3","options_field":"1","tireWidth":"235","tireRatio":"35","rimSize":"19"}, {"id":"1404","Size":"225\/35R19","idTire":"3","options_field":"1","tireWidth":"225","tireRatio":"35","rimSize":"19"}, {"id":"1403","Size":"275\/35R18","idTire":"3","options_field":"1","tireWidth":"275","tireRatio":"35","rimSize":"18"}, {"id":"1402","Size":"265\/35R18","idTire":"3","options_field":"1","tireWidth":"265","tireRatio":"35","rimSize":"18"}, {"id":"1401","Size":"215\/35R18","idTire":"3","options_field":"1","tireWidth":"215","tireRatio":"35","rimSize":"18"}, {"id":"1400","Size":"255\/30R24","idTire":"3","options_field":"1","tireWidth":"255","tireRatio":"30","rimSize":"24"}, {"id":"1399","Size":"245\/30R22 ","idTire":"3","options_field":"1","tireWidth":"245","tireRatio":"30","rimSize":"22"}, {"id":"1398","Size":"275\/30R20","idTire":"3","options_field":"1","tireWidth":"275","tireRatio":"30","rimSize":"20"}, {"id":"2125","Size":"205\/55R16","idTire":"482","options_field":"1","tireWidth":"205","tireRatio":"55","rimSize":"16"}, {"id":"1252","Size":"285\/45R19","idTire":"328","options_field":"1","tireWidth":"285","tireRatio":"45","rimSize":"19"}, {"id":"1251","Size":"275\/45R20","idTire":"328","options_field":"1","tireWidth":"275","tireRatio":"45","rimSize":"20"}, {"id":"1250","Size":"275\/40R20","idTire":"328","options_field":"1","tireWidth":"275","tireRatio":"40","rimSize":"20"}, {"id":"1249","Size":"265\/60R18","idTire":"328","options_field":"1","tireWidth":"265","tireRatio":"60","rimSize":"18"}, {"id":"1248","Size":"265\/45R20","idTire":"328","options_field":"1","tireWidth":"265","tireRatio":"45","rimSize":"20"}, {"id":"1247","Size":"255\/65R16","idTire":"328","options_field":"1","tireWidth":"255","tireRatio":"65","rimSize":"16"}, {"id":"1246","Size":"255\/60R18","idTire":"328","options_field":"1","tireWidth":"255","tireRatio":"60","rimSize":"18"}, {"id":"1245","Size":"255\/55R18","idTire":"328","options_field":"1","tireWidth":"255","tireRatio":"55","rimSize":"18"}, {"id":"1244","Size":"255\/50R19","idTire":"328","options_field":"1","tireWidth":"255","tireRatio":"50","rimSize":"19"}, {"id":"1243","Size":"255\/45R20","idTire":"328","options_field":"1","tireWidth":"255","tireRatio":"45","rimSize":"20"}, {"id":"1242","Size":"245\/60R18","idTire":"328","options_field":"1","tireWidth":"245","tireRatio":"60","rimSize":"18"}, {"id":"1241","Size":"235\/65R17","idTire":"328","options_field":"1","tireWidth":"235","tireRatio":"65","rimSize":"17"}, {"id":"1240","Size":"235\/60R18","idTire":"328","options_field":"1","tireWidth":"235","tireRatio":"60","rimSize":"18"}, {"id":"1239","Size":"235\/60R17","idTire":"328","options_field":"1","tireWidth":"235","tireRatio":"60","rimSize":"17"}, {"id":"1238","Size":"235\/55R19","idTire":"328","options_field":"1","tireWidth":"235","tireRatio":"55","rimSize":"19"}, {"id":"2024","Size":"235\/55R19","idTire":"297","options_field":"1","tireWidth":"235","tireRatio":"55","rimSize":"19"}, {"id":"2023","Size":"185\/55R16","idTire":"297","options_field":"1","tireWidth":"185","tireRatio":"55","rimSize":"16"}, {"id":"2022","Size":"205\/50R17","idTire":"297","options_field":"1","tireWidth":"205","tireRatio":"50","rimSize":"17"}, {"id":"2021","Size":"185\/50R16","idTire":"297","options_field":"1","tireWidth":"185","tireRatio":"50","rimSize":"16"}, {"id":"2020","Size":"195\/45R15","idTire":"297","options_field":"1","tireWidth":"195","tireRatio":"45","rimSize":"15"}, {"id":"2019","Size":"235\/55R18","idTire":"297","options_field":"1","tireWidth":"235","tireRatio":"55","rimSize":"18"}, {"id":"2018","Size":"225\/55R16","idTire":"297","options_field":"1","tireWidth":"225","tireRatio":"55","rimSize":"16"}, {"id":"2017","Size":"215\/55R17","idTire":"297","options_field":"1","tireWidth":"215","tireRatio":"55","rimSize":"17"}, {"id":"2016","Size":"215\/55R16","idTire":"297","options_field":"1","tireWidth":"215","tireRatio":"55","rimSize":"16"}, {"id":"2015","Size":"205\/55R16","idTire":"297","options_field":"1","tireWidth":"205","tireRatio":"55","rimSize":"16"}, {"id":"2014","Size":"245\/50R18","idTire":"297","options_field":"1","tireWidth":"245","tireRatio":"50","rimSize":"18"}, {"id":"2013","Size":"235\/50R18","idTire":"297","options_field":"1","tireWidth":"235","tireRatio":"50","rimSize":"18"}, {"id":"2012","Size":"225\/50R17","idTire":"297","options_field":"1","tireWidth":"225","tireRatio":"50","rimSize":"17"}, {"id":"2011","Size":"225\/50R16","idTire":"297","options_field":"1","tireWidth":"225","tireRatio":"50","rimSize":"16"}, {"id":"2010","Size":"215\/50R17","idTire":"297","options_field":"1","tireWidth":"215","tireRatio":"50","rimSize":"17"}, {"id":"2009","Size":"205\/50R16","idTire":"297","options_field":"1","tireWidth":"205","tireRatio":"50","rimSize":"16"}, {"id":"2008","Size":"255\/45R18","idTire":"297","options_field":"1","tireWidth":"255","tireRatio":"45","rimSize":"18"}, {"id":"2007","Size":"245\/45R19","idTire":"297","options_field":"1","tireWidth":"245","tireRatio":"45","rimSize":"19"}, {"id":"2006","Size":"245\/45R18","idTire":"297","options_field":"1","tireWidth":"245","tireRatio":"45","rimSize":"18"}, {"id":"2005","Size":"245\/45R17","idTire":"297","options_field":"1","tireWidth":"245","tireRatio":"45","rimSize":"17"}, {"id":"2004","Size":"245\/45R16","idTire":"297","options_field":"1","tireWidth":"245","tireRatio":"45","rimSize":"16"}, {"id":"2003","Size":"235\/45R18","idTire":"297","options_field":"1","tireWidth":"235","tireRatio":"45","rimSize":"18"}, {"id":"2002","Size":"235\/45R17","idTire":"297","options_field":"1","tireWidth":"235","tireRatio":"45","rimSize":"17"}, {"id":"2001","Size":"225\/45R18","idTire":"297","options_field":"1","tireWidth":"225","tireRatio":"45","rimSize":"18"}, {"id":"2000","Size":"225\/45R17","idTire":"297","options_field":"1","tireWidth":"225","tireRatio":"45","rimSize":"17"}, {"id":"1999","Size":"215\/45R17","idTire":"297","options_field":"1","tireWidth":"215","tireRatio":"45","rimSize":"17"}, {"id":"1998","Size":"205\/45R17","idTire":"297","options_field":"1","tireWidth":"205","tireRatio":"45","rimSize":"17"}, {"id":"1997","Size":"205\/45R16","idTire":"297","options_field":"1","tireWidth":"205","tireRatio":"45","rimSize":"16"}, {"id":"1996","Size":"195\/45R16","idTire":"297","options_field":"1","tireWidth":"195","tireRatio":"45","rimSize":"16"}, {"id":"1995","Size":"255\/40R18","idTire":"297","options_field":"1","tireWidth":"255","tireRatio":"40","rimSize":"18"}, {"id":"1994","Size":"255\/40R17","idTire":"297","options_field":"1","tireWidth":"255","tireRatio":"40","rimSize":"17"}, {"id":"1993","Size":"245\/40R19","idTire":"297","options_field":"1","tireWidth":"245","tireRatio":"40","rimSize":"19"}, {"id":"1992","Size":"245\/40R18","idTire":"297","options_field":"1","tireWidth":"245","tireRatio":"40","rimSize":"18"}, {"id":"1991","Size":"245\/40R17","idTire":"297","options_field":"1","tireWidth":"245","tireRatio":"40","rimSize":"17"}, {"id":"1990","Size":"235\/40R18","idTire":"297","options_field":"1","tireWidth":"235","tireRatio":"40","rimSize":"18"}, {"id":"1989","Size":"235\/40R17","idTire":"297","options_field":"1","tireWidth":"235","tireRatio":"40","rimSize":"17"}, {"id":"1988","Size":"225\/40R18","idTire":"297","options_field":"1","tireWidth":"225","tireRatio":"40","rimSize":"18"}, {"id":"1987","Size":"215\/40R18","idTire":"297","options_field":"1","tireWidth":"215","tireRatio":"40","rimSize":"18"}, {"id":"1853","Size":"LT235\/75R15","idTire":"321","options_field":"1","tireWidth":"235","tireRatio":"75","rimSize":"15"}, {"id":"1852","Size":"LT235\/85R16","idTire":"321","options_field":"1","tireWidth":"235","tireRatio":"85","rimSize":"16"}, {"id":"1851","Size":"245\/75R16","idTire":"321","options_field":"1","tireWidth":"245","tireRatio":"75","rimSize":"16"}, {"id":"1734","Size":"255\/65R17","idTire":"13","options_field":"1","tireWidth":"255","tireRatio":"65","rimSize":"17"}, {"id":"1733","Size":"235\/65R17","idTire":"13","options_field":"1","tireWidth":"235","tireRatio":"65","rimSize":"17"}, {"id":"1732","Size":"285\/60R18","idTire":"13","options_field":"1","tireWidth":"285","tireRatio":"60","rimSize":"18"}, {"id":"1731","Size":"265\/60R18","idTire":"13","options_field":"1","tireWidth":"265","tireRatio":"60","rimSize":"18"}, {"id":"1730","Size":"275\/60R17","idTire":"13","options_field":"1","tireWidth":"275","tireRatio":"60","rimSize":"17"}, {"id":"1729","Size":"265\/60R17","idTire":"13","options_field":"1","tireWidth":"265","tireRatio":"60","rimSize":"17"}, {"id":"1728","Size":"255\/60R17","idTire":"13","options_field":"1","tireWidth":"255","tireRatio":"60","rimSize":"17"}, {"id":"1727","Size":"235\/60R16","idTire":"13","options_field":"1","tireWidth":"235","tireRatio":"60","rimSize":"16"}, {"id":"1726","Size":"275\/55R20","idTire":"13","options_field":"1","tireWidth":"275","tireRatio":"55","rimSize":"20"}, {"id":"1725","Size":"255\/55R18","idTire":"13","options_field":"1","tireWidth":"255","tireRatio":"55","rimSize":"18"}, {"id":"1724","Size":"275\/55R17","idTire":"13","options_field":"1","tireWidth":"275","tireRatio":"55","rimSize":"17"}, {"id":"1723","Size":"285\/50R20","idTire":"13","options_field":"1","tireWidth":"285","tireRatio":"50","rimSize":"20"}, {"id":"1722","Size":"265\/50R20","idTire":"13","options_field":"1","tireWidth":"265","tireRatio":"50","rimSize":"20"}, {"id":"1721","Size":"255\/50R20","idTire":"13","options_field":"1","tireWidth":"255","tireRatio":"50","rimSize":"20"}, {"id":"1720","Size":"255\/50R19","idTire":"13","options_field":"1","tireWidth":"255","tireRatio":"50","rimSize":"19"}, {"id":"1719","Size":"305\/45R22","idTire":"13","options_field":"1","tireWidth":"305","tireRatio":"45","rimSize":"22"}, {"id":"1718","Size":"285\/45R22","idTire":"13","options_field":"1","tireWidth":"285","tireRatio":"45","rimSize":"22"}, {"id":"1717","Size":"295\/45R20","idTire":"13","options_field":"1","tireWidth":"295","tireRatio":"45","rimSize":"20"}, {"id":"1716","Size":"275\/45R20","idTire":"13","options_field":"1","tireWidth":"275","tireRatio":"45","rimSize":"20"}, {"id":"1715","Size":"265\/45R20","idTire":"13","options_field":"1","tireWidth":"265","tireRatio":"45","rimSize":"20"}, {"id":"1714","Size":"285\/45R19","idTire":"13","options_field":"1","tireWidth":"285","tireRatio":"45","rimSize":"19"}, {"id":"1713","Size":"305\/40R22","idTire":"13","options_field":"1","tireWidth":"305","tireRatio":"40","rimSize":"22"}, {"id":"1712","Size":"295\/40R20","idTire":"13","options_field":"1","tireWidth":"295","tireRatio":"40","rimSize":"20"}, {"id":"1711","Size":"275\/40R20","idTire":"13","options_field":"1","tireWidth":"275","tireRatio":"40","rimSize":"20"}, {"id":"1710","Size":"305\/35R24","idTire":"13","options_field":"1","tireWidth":"305","tireRatio":"35","rimSize":"24"}, {"id":"1709","Size":"295\/35R24","idTire":"13","options_field":"1","tireWidth":"295","tireRatio":"35","rimSize":"24"}, {"id":"1708","Size":"285\/35R22","idTire":"13","options_field":"1","tireWidth":"285","tireRatio":"35","rimSize":"22"}, {"id":"1707","Size":"265\/35R22","idTire":"13","options_field":"1","tireWidth":"265","tireRatio":"35","rimSize":"22"}, {"id":"1706","Size":"295\/30R22","idTire":"13","options_field":"1","tireWidth":"295","tireRatio":"30","rimSize":"22"}, {"id":"1705","Size":"255\/30R22","idTire":"13","options_field":"1","tireWidth":"255","tireRatio":"30","rimSize":"22"}, {"id":"2143","Size":"225\/50R18","idTire":"482","options_field":"1","tireWidth":"225","tireRatio":"50","rimSize":"18"}, {"id":"2142","Size":"215\/45R18","idTire":"482","options_field":"1","tireWidth":"215","tireRatio":"45","rimSize":"18"}, {"id":"2141","Size":"245\/40R18","idTire":"482","options_field":"1","tireWidth":"245","tireRatio":"40","rimSize":"18"}, {"id":"2140","Size":"235\/40R18","idTire":"482","options_field":"1","tireWidth":"235","tireRatio":"40","rimSize":"18"}, {"id":"2139","Size":"225\/40R18","idTire":"482","options_field":"1","tireWidth":"225","tireRatio":"40","rimSize":"18"}, {"id":"2138","Size":"235\/55R17","idTire":"482","options_field":"1","tireWidth":"235","tireRatio":"55","rimSize":"17"}, {"id":"1873","Size":"205\/55R16","idTire":"55","options_field":"1","tireWidth":"205","tireRatio":"55","rimSize":"16"}, {"id":"1872","Size":"215\/45R17","idTire":"55","options_field":"1","tireWidth":"215","tireRatio":"45","rimSize":"17"}, {"id":"1871","Size":"215\/45R17","idTire":"55","options_field":"1","tireWidth":"215","tireRatio":"45","rimSize":"17"}, {"id":"1870","Size":"205\/55R16","idTire":"55","options_field":"1","tireWidth":"205","tireRatio":"55","rimSize":"16"}, {"id":"1777","Size":"265\/75R16","idTire":"14","options_field":"1","tireWidth":"265","tireRatio":"75","rimSize":"16"}, {"id":"1776","Size":"245\/75R16","idTire":"14","options_field":"1","tireWidth":"245","tireRatio":"75","rimSize":"16"}, {"id":"1775","Size":"225\/75R16","idTire":"14","options_field":"1","tireWidth":"225","tireRatio":"75","rimSize":"16"}, {"id":"1774","Size":"265\/75R15","idTire":"14","options_field":"1","tireWidth":"265","tireRatio":"75","rimSize":"15"}, {"id":"1773","Size":"235\/75R15","idTire":"14","options_field":"1","tireWidth":"235","tireRatio":"75","rimSize":"15"}, {"id":"1772","Size":"225\/75R15","idTire":"14","options_field":"1","tireWidth":"225","tireRatio":"75","rimSize":"15"}, {"id":"1771","Size":"215\/75R15","idTire":"14","options_field":"1","tireWidth":"215","tireRatio":"75","rimSize":"15"}, {"id":"1770","Size":"255\/70R18","idTire":"14","options_field":"1","tireWidth":"255","tireRatio":"70","rimSize":"18"}, {"id":"1769","Size":"265\/70R17","idTire":"14","options_field":"1","tireWidth":"265","tireRatio":"70","rimSize":"17"}, {"id":"1768","Size":"245\/70R17","idTire":"14","options_field":"1","tireWidth":"245","tireRatio":"70","rimSize":"17"}, {"id":"1767","Size":"235\/70R17","idTire":"14","options_field":"1","tireWidth":"235","tireRatio":"70","rimSize":"17"}, {"id":"1766","Size":"275\/70R16","idTire":"14","options_field":"1","tireWidth":"275","tireRatio":"70","rimSize":"16"}, {"id":"1765","Size":"265\/70R16","idTire":"14","options_field":"1","tireWidth":"265","tireRatio":"70","rimSize":"16"}, {"id":"1764","Size":"255\/70R16","idTire":"14","options_field":"1","tireWidth":"255","tireRatio":"70","rimSize":"16"}, {"id":"1763","Size":"245\/70R16","idTire":"14","options_field":"1","tireWidth":"245","tireRatio":"70","rimSize":"16"}, {"id":"1762","Size":"235\/70R16","idTire":"14","options_field":"1","tireWidth":"235","tireRatio":"70","rimSize":"16"}, {"id":"1761","Size":"265\/70R15","idTire":"14","options_field":"1","tireWidth":"265","tireRatio":"70","rimSize":"15"}, {"id":"1760","Size":"255\/70R15","idTire":"14","options_field":"1","tireWidth":"255","tireRatio":"70","rimSize":"15"}, {"id":"1759","Size":"235\/70R15","idTire":"14","options_field":"1","tireWidth":"235","tireRatio":"70","rimSize":"15"}, {"id":"1758","Size":"225\/70R15","idTire":"14","options_field":"1","tireWidth":"225","tireRatio":"70","rimSize":"15"}, {"id":"1757","Size":"275\/65R18","idTire":"14","options_field":"1","tireWidth":"275","tireRatio":"65","rimSize":"18"}, {"id":"1756","Size":"265\/65R18","idTire":"14","options_field":"1","tireWidth":"265","tireRatio":"65","rimSize":"18"}, {"id":"1755","Size":"235\/65R18","idTire":"14","options_field":"1","tireWidth":"235","tireRatio":"65","rimSize":"18"}, {"id":"1754","Size":"265\/65R17","idTire":"14","options_field":"1","tireWidth":"265","tireRatio":"65","rimSize":"17"}, {"id":"1753","Size":"255\/65R17","idTire":"14","options_field":"1","tireWidth":"255","tireRatio":"65","rimSize":"17"}, {"id":"1752","Size":"245\/65R17","idTire":"14","options_field":"1","tireWidth":"245","tireRatio":"65","rimSize":"17"}, {"id":"1751","Size":"235\/65R17","idTire":"14","options_field":"1","tireWidth":"235","tireRatio":"65","rimSize":"17"}, {"id":"1750","Size":"225\/65R17","idTire":"14","options_field":"1","tireWidth":"225","tireRatio":"65","rimSize":"17"}, {"id":"1749","Size":"275\/60R20","idTire":"14","options_field":"1","tireWidth":"275","tireRatio":"60","rimSize":"20"}, {"id":"1748","Size":"275\/60R18","idTire":"14","options_field":"1","tireWidth":"275","tireRatio":"60","rimSize":"18"}, {"id":"1747","Size":"245\/60R18","idTire":"14","options_field":"1","tireWidth":"245","tireRatio":"60","rimSize":"18"}, {"id":"1746","Size":"235\/60R18","idTire":"14","options_field":"1","tireWidth":"235","tireRatio":"60","rimSize":"18"}, {"id":"1745","Size":"235\/60R17","idTire":"14","options_field":"1","tireWidth":"235","tireRatio":"60","rimSize":"17"}, {"id":"1781","Size":"LT235\/85R16","idTire":"12","options_field":"1","tireWidth":"235","tireRatio":"85","rimSize":"16"}, {"id":"1780","Size":"LT265\/75R16","idTire":"12","options_field":"1","tireWidth":"265","tireRatio":"75","rimSize":"16"}, {"id":"1779","Size":"LT235\/75R15","idTire":"12","options_field":"1","tireWidth":"235","tireRatio":"75","rimSize":"15"}, {"id":"1778","Size":"31X10.50R15","idTire":"12","options_field":"1","tireWidth":"31","tireRatio":"11","rimSize":"15"}, {"id":"944","Size":"225\/60R16","idTire":"23","options_field":"1","tireWidth":"225","tireRatio":"60","rimSize":"16"}, {"id":"945","Size":"225\/50R17","idTire":"23","options_field":"1","tireWidth":"225","tireRatio":"50","rimSize":"17"}, {"id":"946","Size":"205\/40R17","idTire":"23","options_field":"1","tireWidth":"205","tireRatio":"40","rimSize":"17"}, {"id":"947","Size":"205\/60R15","idTire":"23","options_field":"1","tireWidth":"205","tireRatio":"60","rimSize":"15"}, {"id":"948","Size":"205\/50R17","idTire":"23","options_field":"1","tireWidth":"205","tireRatio":"50","rimSize":"17"}, {"id":"949","Size":"195\/60R15","idTire":"23","options_field":"1","tireWidth":"195","tireRatio":"60","rimSize":"15"}, {"id":"950","Size":"235\/45R17","idTire":"23","options_field":"1","tireWidth":"235","tireRatio":"45","rimSize":"17"}, {"id":"951","Size":"235\/55R17","idTire":"23","options_field":"1","tireWidth":"235","tireRatio":"55","rimSize":"17"}, {"id":"952","Size":"225\/45R17","idTire":"23","options_field":"1","tireWidth":"225","tireRatio":"45","rimSize":"17"}, {"id":"953","Size":"225\/55R17","idTire":"23","options_field":"1","tireWidth":"225","tireRatio":"55","rimSize":"17"}, {"id":"954","Size":"215\/45R17","idTire":"23","options_field":"1","tireWidth":"215","tireRatio":"45","rimSize":"17"}, {"id":"955","Size":"225\/55R16","idTire":"23","options_field":"1","tireWidth":"225","tireRatio":"55","rimSize":"16"}, {"id":"956","Size":"235\/40R18","idTire":"23","options_field":"1","tireWidth":"235","tireRatio":"40","rimSize":"18"}, {"id":"957","Size":"195\/65R15","idTire":"23","options_field":"1","tireWidth":"195","tireRatio":"65","rimSize":"15"}, {"id":"958","Size":"215\/55R16","idTire":"23","options_field":"1","tireWidth":"215","tireRatio":"55","rimSize":"16"}, {"id":"959","Size":"225\/40R18","idTire":"23","options_field":"1","tireWidth":"225","tireRatio":"40","rimSize":"18"}, {"id":"960","Size":"185\/65R15","idTire":"23","options_field":"1","tireWidth":"185","tireRatio":"65","rimSize":"15"}, {"id":"961","Size":"205\/55R16","idTire":"23","options_field":"1","tireWidth":"205","tireRatio":"55","rimSize":"16"}, {"id":"962","Size":"215\/40R17","idTire":"23","options_field":"1","tireWidth":"215","tireRatio":"40","rimSize":"17"}, {"id":"974","Size":"185\/55R15","idTire":"168","options_field":"1","tireWidth":"185","tireRatio":"55","rimSize":"15"}, {"id":"975","Size":"195\/60R16","idTire":"168","options_field":"1","tireWidth":"195","tireRatio":"60","rimSize":"16"}, {"id":"976","Size":"175\/70R14","idTire":"168","options_field":"1","tireWidth":"175","tireRatio":"70","rimSize":"14"}, {"id":"977","Size":"195\/55R15","idTire":"168","options_field":"1","tireWidth":"195","tireRatio":"55","rimSize":"15"}, {"id":"978","Size":"205\/60R16","idTire":"168","options_field":"1","tireWidth":"205","tireRatio":"60","rimSize":"16"}, {"id":"979","Size":"185\/70R14","idTire":"168","options_field":"1","tireWidth":"185","tireRatio":"70","rimSize":"14"}, {"id":"980","Size":"175\/65R14XL","idTire":"168","options_field":"1","tireWidth":"175","tireRatio":"65","rimSize":"14"}, {"id":"981","Size":"205\/55R16","idTire":"168","options_field":"1","tireWidth":"205","tireRatio":"55","rimSize":"16"}, {"id":"982","Size":"225\/60R16","idTire":"168","options_field":"1","tireWidth":"225","tireRatio":"60","rimSize":"16"}, {"id":"983","Size":"205\/70R15","idTire":"168","options_field":"1","tireWidth":"205","tireRatio":"70","rimSize":"15"}, {"id":"984","Size":"185\/65R14XL","idTire":"168","options_field":"1","tireWidth":"185","tireRatio":"65","rimSize":"14"}, {"id":"985","Size":"215\/55R16","idTire":"168","options_field":"1","tireWidth":"215","tireRatio":"55","rimSize":"16"}, {"id":"986","Size":"215\/60R17","idTire":"168","options_field":"1","tireWidth":"215","tireRatio":"60","rimSize":"17"}, {"id":"987","Size":"","idTire":"168","options_field":"1","tireWidth":null,"tireRatio":null,"rimSize":null}, {"id":"988","Size":"185\/65R15XL","idTire":"168","options_field":"1","tireWidth":"185","tireRatio":"65","rimSize":"15"}, {"id":"989","Size":"215\/55R17","idTire":"168","options_field":"1","tireWidth":"215","tireRatio":"55","rimSize":"17"}, {"id":"990","Size":"195\/65R15","idTire":"168","options_field":"1","tireWidth":"195","tireRatio":"65","rimSize":"15"}, {"id":"991","Size":"215\/60R16XL","idTire":"168","options_field":"1","tireWidth":"215","tireRatio":"60","rimSize":"16"}, {"id":"992","Size":"185\/60R14","idTire":"168","options_field":"1","tireWidth":"185","tireRatio":"60","rimSize":"14"}, {"id":"993","Size":"205\/65R15","idTire":"168","options_field":"1","tireWidth":"205","tireRatio":"65","rimSize":"15"}, {"id":"994","Size":"195\/50R15","idTire":"168","options_field":"1","tireWidth":"195","tireRatio":"50","rimSize":"15"}, {"id":"995","Size":"185\/60R15","idTire":"168","options_field":"1","tireWidth":"185","tireRatio":"60","rimSize":"15"}, {"id":"996","Size":"215\/65R16","idTire":"168","options_field":"1","tireWidth":"215","tireRatio":"65","rimSize":"16"}, {"id":"997","Size":"225\/50R17","idTire":"168","options_field":"1","tireWidth":"225","tireRatio":"50","rimSize":"17"}, {"id":"998","Size":"195\/60R15","idTire":"168","options_field":"1","tireWidth":"195","tireRatio":"60","rimSize":"15"}, {"id":"999","Size":"175\/70R13","idTire":"168","options_field":"1","tireWidth":"175","tireRatio":"70","rimSize":"13"}, {"id":"1006","Size":"P225\/55R18 ","idTire":"405","options_field":"1","tireWidth":"225","tireRatio":"55","rimSize":"18"}, {"id":"1857","Size":"195\/65R15","idTire":"55","options_field":"1","tireWidth":"195","tireRatio":"65","rimSize":"15"}, {"id":"1856","Size":"235\/45R18","idTire":"55","options_field":"1","tireWidth":"235","tireRatio":"45","rimSize":"18"}, {"id":"1826","Size":"235\/60R18","idTire":"318","options_field":"1","tireWidth":"235","tireRatio":"60","rimSize":"18"}, {"id":"1825","Size":"235\/55R18","idTire":"318","options_field":"1","tireWidth":"235","tireRatio":"55","rimSize":"18"}, {"id":"1824","Size":"235\/65R18","idTire":"318","options_field":"1","tireWidth":"235","tireRatio":"65","rimSize":"18"}, {"id":"1823","Size":"235\/65R17","idTire":"318","options_field":"1","tireWidth":"235","tireRatio":"65","rimSize":"17"}, {"id":"1822","Size":"235\/65R16","idTire":"318","options_field":"1","tireWidth":"235","tireRatio":"65","rimSize":"16"}, {"id":"1821","Size":"225\/65R17","idTire":"318","options_field":"1","tireWidth":"225","tireRatio":"65","rimSize":"17"}, {"id":"1820","Size":"225\/65R16","idTire":"318","options_field":"1","tireWidth":"225","tireRatio":"65","rimSize":"16"}, {"id":"1819","Size":"215\/65R17","idTire":"318","options_field":"1","tireWidth":"215","tireRatio":"65","rimSize":"17"}, {"id":"1818","Size":"235\/60R17","idTire":"318","options_field":"1","tireWidth":"235","tireRatio":"60","rimSize":"17"}, {"id":"1817","Size":"225\/60R17","idTire":"318","options_field":"1","tireWidth":"225","tireRatio":"60","rimSize":"17"}, {"id":"1816","Size":"215\/60R17","idTire":"318","options_field":"1","tireWidth":"215","tireRatio":"60","rimSize":"17"}, {"id":"1237","Size":"235\/55R18","idTire":"328","options_field":"1","tireWidth":"235","tireRatio":"55","rimSize":"18"}, {"id":"1236","Size":"225\/60R17","idTire":"328","options_field":"1","tireWidth":"225","tireRatio":"60","rimSize":"17"}, {"id":"1235","Size":"225\/55R18","idTire":"328","options_field":"1","tireWidth":"225","tireRatio":"55","rimSize":"18"}, {"id":"1234","Size":"LT265\/75R16","idTire":"323","options_field":"1","tireWidth":"265","tireRatio":"75","rimSize":"16"}, {"id":"1233","Size":"LT245\/75R16","idTire":"323","options_field":"1","tireWidth":"245","tireRatio":"75","rimSize":"16"}, {"id":"1232","Size":"LT235\/85R16","idTire":"323","options_field":"1","tireWidth":"235","tireRatio":"85","rimSize":"16"}, {"id":"1231","Size":"LT235\/80R17","idTire":"323","options_field":"1","tireWidth":"235","tireRatio":"80","rimSize":"17"}, {"id":"1230","Size":"LT225\/75R16","idTire":"323","options_field":"1","tireWidth":"225","tireRatio":"75","rimSize":"16"}, {"id":"1229","Size":"LT215\/85R16","idTire":"323","options_field":"1","tireWidth":"215","tireRatio":"85","rimSize":"16"}, {"id":"1228","Size":"265\/70R17","idTire":"323","options_field":"1","tireWidth":"265","tireRatio":"70","rimSize":"17"}, {"id":"1227","Size":"255\/70R17","idTire":"323","options_field":"1","tireWidth":"255","tireRatio":"70","rimSize":"17"}, {"id":"1226","Size":"255\/65R18","idTire":"323","options_field":"1","tireWidth":"255","tireRatio":"65","rimSize":"18"}, {"id":"1225","Size":"255\/65R16","idTire":"323","options_field":"1","tireWidth":"255","tireRatio":"65","rimSize":"16"}, {"id":"1224","Size":"235\/75R16","idTire":"323","options_field":"1","tireWidth":"235","tireRatio":"75","rimSize":"16"}, {"id":"1223","Size":"235\/70R16","idTire":"323","options_field":"1","tireWidth":"235","tireRatio":"70","rimSize":"16"}, {"id":"1222","Size":"235\/65R16","idTire":"323","options_field":"1","tireWidth":"235","tireRatio":"65","rimSize":"16"}, {"id":"1221","Size":"225\/70R16","idTire":"323","options_field":"1","tireWidth":"225","tireRatio":"70","rimSize":"16"}, {"id":"1986","Size":"215\/40R17","idTire":"297","options_field":"1","tireWidth":"215","tireRatio":"40","rimSize":"17"}, {"id":"1985","Size":"215\/40R16","idTire":"297","options_field":"1","tireWidth":"215","tireRatio":"40","rimSize":"16"}, {"id":"1984","Size":"205\/40R17","idTire":"297","options_field":"1","tireWidth":"205","tireRatio":"40","rimSize":"17"}, {"id":"1983","Size":"205\/40R16","idTire":"297","options_field":"1","tireWidth":"205","tireRatio":"40","rimSize":"16"}, {"id":"1982","Size":"255\/35R19","idTire":"297","options_field":"1","tireWidth":"255","tireRatio":"35","rimSize":"19"}, {"id":"1981","Size":"255\/35R18","idTire":"297","options_field":"1","tireWidth":"255","tireRatio":"35","rimSize":"18"}, {"id":"1980","Size":"245\/35R18","idTire":"297","options_field":"1","tireWidth":"245","tireRatio":"35","rimSize":"18"}, {"id":"1979","Size":"235\/35R19","idTire":"297","options_field":"1","tireWidth":"235","tireRatio":"35","rimSize":"19"}, {"id":"1815","Size":"215\/60R16","idTire":"318","options_field":"1","tireWidth":"215","tireRatio":"60","rimSize":"16"}, {"id":"1814","Size":"225\/55R17","idTire":"318","options_field":"1","tireWidth":"225","tireRatio":"55","rimSize":"17"}, {"id":"1850","Size":"265\/75R16","idTire":"321","options_field":"1","tireWidth":"265","tireRatio":"75","rimSize":"16"}, {"id":"1849","Size":"LT245\/75R16","idTire":"321","options_field":"1","tireWidth":"245","tireRatio":"75","rimSize":"16"}, {"id":"1848","Size":"LT265\/75R16","idTire":"321","options_field":"1","tireWidth":"265","tireRatio":"75","rimSize":"16"}, {"id":"1847","Size":"235\/70R16","idTire":"321","options_field":"1","tireWidth":"235","tireRatio":"70","rimSize":"16"}, {"id":"1846","Size":"245\/70R16","idTire":"321","options_field":"1","tireWidth":"245","tireRatio":"70","rimSize":"16"}, {"id":"1845","Size":"255\/70R16","idTire":"321","options_field":"1","tireWidth":"255","tireRatio":"70","rimSize":"16"}, {"id":"1844","Size":"265\/70R16","idTire":"321","options_field":"1","tireWidth":"265","tireRatio":"70","rimSize":"16"}, {"id":"1843","Size":"LT245\/75R17","idTire":"321","options_field":"1","tireWidth":"245","tireRatio":"75","rimSize":"17"}, {"id":"1842","Size":"245\/70R17","idTire":"321","options_field":"1","tireWidth":"245","tireRatio":"70","rimSize":"17"}, {"id":"1841","Size":"265\/70R17","idTire":"321","options_field":"1","tireWidth":"265","tireRatio":"70","rimSize":"17"}, {"id":"1840","Size":"LT245\/70R17","idTire":"321","options_field":"1","tireWidth":"245","tireRatio":"70","rimSize":"17"}, {"id":"1839","Size":"LT265\/70R17","idTire":"321","options_field":"1","tireWidth":"265","tireRatio":"70","rimSize":"17"}, {"id":"1838","Size":"235\/65R17","idTire":"321","options_field":"1","tireWidth":"235","tireRatio":"65","rimSize":"17"}, {"id":"1837","Size":"245\/65R17","idTire":"321","options_field":"1","tireWidth":"245","tireRatio":"65","rimSize":"17"}, {"id":"1836","Size":"255\/65R17","idTire":"321","options_field":"1","tireWidth":"255","tireRatio":"65","rimSize":"17"}, {"id":"1835","Size":"265\/65R17","idTire":"321","options_field":"1","tireWidth":"265","tireRatio":"65","rimSize":"17"}, {"id":"1834","Size":"265\/65R18","idTire":"321","options_field":"1","tireWidth":"265","tireRatio":"65","rimSize":"18"}, {"id":"1833","Size":"275\/65R18","idTire":"321","options_field":"1","tireWidth":"275","tireRatio":"65","rimSize":"18"}, {"id":"1832","Size":"265\/60R18","idTire":"321","options_field":"1","tireWidth":"265","tireRatio":"60","rimSize":"18"}, {"id":"1831","Size":"275\/60R20","idTire":"321","options_field":"1","tireWidth":"275","tireRatio":"60","rimSize":"20"}, {"id":"1830","Size":"275\/55R20XL","idTire":"321","options_field":"1","tireWidth":"275","tireRatio":"55","rimSize":"20"}, {"id":"1829","Size":"30x9.50R15LT","idTire":"321","options_field":"1","tireWidth":"30","tireRatio":"10","rimSize":"15"}, {"id":"1828","Size":"31x10.50R15LT","idTire":"321","options_field":"1","tireWidth":"31","tireRatio":"11","rimSize":"15"}, {"id":"1827","Size":"LT225\/75R16","idTire":"321","options_field":"1","tireWidth":"225","tireRatio":"75","rimSize":"16"}, {"id":"1978","Size":"225\/35R19","idTire":"297","options_field":"1","tireWidth":"225","tireRatio":"35","rimSize":"19"}, {"id":"1977","Size":"225\/35R18","idTire":"297","options_field":"1","tireWidth":"225","tireRatio":"35","rimSize":"18"}, {"id":"1976","Size":"215\/35R18","idTire":"297","options_field":"1","tireWidth":"215","tireRatio":"35","rimSize":"18"}, {"id":"1975","Size":"275\/30R20","idTire":"297","options_field":"1","tireWidth":"275","tireRatio":"30","rimSize":"20"}, {"id":"1974","Size":"275\/30R19","idTire":"297","options_field":"1","tireWidth":"275","tireRatio":"30","rimSize":"19"}, {"id":"1855","Size":"215\/45R17","idTire":"55","options_field":"1","tireWidth":"215","tireRatio":"45","rimSize":"17"}, {"id":"2144","Size":"215\/55R18","idTire":"482","options_field":"1","tireWidth":"215","tireRatio":"55","rimSize":"18"}]
